yasmon/__init__.py
yasmon/callbacks.py
yasmon/cli.py
yasmon/loggers.py
yasmon/processor.py
yasmon/tasks.py
yasmon-0.3.0.dist-info/LICENSE
yasmon-0.3.0.dist-info/METADATA
yasmon-0.3.0.dist-info/WHEEL
yasmon-0.3.0.dist-info/entry_points.txt
yasmon-0.3.0.dist-info/top_level.txt
yasmon-0.3.0.dist-info/RECORD
