Metadata-Version: 2.1
Name: yasmon
Version: 0.3.0
Summary: Python system monitor with callbacks and logging
Author-email: "Michał Ł. Mika" <michal@mika.sh>
Project-URL: Homepage, https://github.com/m1ka05/yasmon
Project-URL: Bug Tracker, https://github.com/m1ka05/yasmon/issues
Classifier: Programming Language :: Python :: 3
Classifier: License :: OSI Approved :: MIT License
Classifier: Operating System :: POSIX :: Linux
Requires-Python: >=3.11
License-File: LICENSE
Requires-Dist: watchfiles (==0.18.*)
Requires-Dist: pyyaml
Requires-Dist: nest-asyncio
Requires-Dist: types-PyYAML
Requires-Dist: loguru
Requires-Dist: argparse
Requires-Dist: systemd-python
